surveymars_mcp/__init__.py
surveymars_mcp/scheme.py
surveymars_mcp/server.py
surveymars_mcp/fetcher/__init__.py
surveymars_mcp/fetcher/config.py
mseep_surveymars_mcp-0.1.5.dist-info/METADATA
mseep_surveymars_mcp-0.1.5.dist-info/WHEEL
mseep_surveymars_mcp-0.1.5.dist-info/entry_points.txt
mseep_surveymars_mcp-0.1.5.dist-info/top_level.txt
mseep_surveymars_mcp-0.1.5.dist-info/RECORD
